helper/__init__.py
helper/env_manager.py
helper/main.py
helper/my_speedtest.py
helper/snippets.py
helper/table.py
helper/utils.py
helper/commands/__init__.py
helper/commands/all_info.py
helper/commands/arch.py
helper/commands/docker.py
helper/commands/env.py
helper/commands/file.py
helper/commands/internal_ip.py
helper/commands/nixos.py
helper/commands/public_ip.py
helper/commands/run.py
helper/commands/speed.py
helper/commands/system_info.py
helper/commands/venv.py
helper/commands/verbosity.py
helper_cli-0.1.40.dist-info/METADATA
helper_cli-0.1.40.dist-info/WHEEL
helper_cli-0.1.40.dist-info/entry_points.txt
helper_cli-0.1.40.dist-info/top_level.txt
helper_cli-0.1.40.dist-info/RECORD
