Metadata-Version: 2.4
Name: helper-cli
Version: 0.1.40
Summary: Simple system info CLI
Author-email: Huy Nguyen <huy.ntq02@gmail.com>
License-Expression: GPL-3.0-or-later
Project-URL: Homepage, https://github.com/nguyenhuy158/helper
Project-URL: Documentation, https://nguyenhuy158.github.io/helper/helper.html
Project-URL: Repository, https://github.com/nguyenhuy158/helper
Classifier: Development Status :: 4 - Beta
Classifier: Intended Audience :: Developers
Classifier: Programming Language :: Python :: 3
Classifier: Programming Language :: Python :: 3.8
Classifier: Programming Language :: Python :: 3.9
Classifier: Programming Language :: Python :: 3.10
Classifier: Programming Language :: Python :: 3.11
Classifier: Operating System :: OS Independent
Requires-Python: >=3.8
Requires-Dist: click>=8.0.0
Requires-Dist: speedtest-cli>=2.1.0
